drtensor/__init__.py
drtensor/doctor.py
drtensor/figures.py
drtensor/hooks.py
drtensor/utils.py
drtensor/widgets.py
drtensor-0.0.2.dist-info/LICENSE
drtensor-0.0.2.dist-info/METADATA
drtensor-0.0.2.dist-info/WHEEL
drtensor-0.0.2.dist-info/top_level.txt
drtensor-0.0.2.dist-info/RECORD
