Metadata-Version: 2.1
Name: drtensor
Version: 0.0.2
Summary: Pytorch modeling easier
Author-email: raynardj <b2ray2c@gmail.com>
Project-URL: homepage, https://github.com/raynardj/drtensor
Project-URL: repository, https://github.com/raynardj/drtensor
Keywords: pytorch,debug,tensor
Classifier: Development Status :: 2 - Pre-Alpha
Classifier: Intended Audience :: End Users/Desktop
Classifier: License :: OSI Approved :: GNU General Public License v3 (GPLv3)
Classifier: Programming Language :: Python :: 3.6
Classifier: Programming Language :: Python :: 3.7
Classifier: Programming Language :: Python :: 3.8
Classifier: Programming Language :: Python :: 3.9
Classifier: Programming Language :: Python :: 3.10
Classifier: Programming Language :: Python :: 3.11
Classifier: Programming Language :: Python :: 3.12
License-File: LICENSE
